dcp/__init__.py
dcp/api/__init__.py
dcp/api/compute_for.py
dcp/api/job.py
dcp/api/result_handle.py
dcp/dry/__init__.py
dcp/dry/aio.py
dcp/dry/class_manager.py
dcp/dry/class_registry.py
dcp/dry/package.json
dcp/initialization.py
dcp/js/__init__.py
dcp/js/load_dcp_client.py
dcp/js/package.json
dcp/js/utils.py
dcp-2.0.0.dist-info/METADATA
dcp-2.0.0.dist-info/WHEEL
dcp-2.0.0.dist-info/RECORD
