Metadata-Version: 2.1
Name: dcp
Version: 2.0.0
Summary: A DCP SDK
Home-page: https://github.com/Distributive-Network/bifrost2
License: MIT
Author: Distributive
Author-email: info@distributive.network
Requires-Python: >=3.8,<4.0
Classifier: Development Status :: 2 - Pre-Alpha
Classifier: Intended Audience :: Developers
Classifier: License :: OSI Approved :: MIT License
Classifier: Programming Language :: Python
Classifier: Programming Language :: Python :: 3
Classifier: Programming Language :: Python :: 3.8
Classifier: Programming Language :: Python :: 3.9
Classifier: Programming Language :: Python :: 3.10
Classifier: Programming Language :: Python :: 3.11
Classifier: Programming Language :: Python :: 3.12
Classifier: Topic :: System :: Distributed Computing
Requires-Dist: pythonmonkey (>=0.7.1)
Project-URL: Repository, https://github.com/Distributive-Network/bifrost2
